earthscale/__init__.py
earthscale/cli.py
earthscale/py.typed
earthscale/v1/__init__.py
earthscale/v1/_http_client.py
earthscale/v1/client.py
earthscale/v1/exceptions.py
earthscale/v1/models.py
earthscale/v1/settings.py
earthscale-0.15.0.dist-info/METADATA
earthscale-0.15.0.dist-info/WHEEL
earthscale-0.15.0.dist-info/entry_points.txt
earthscale-0.15.0.dist-info/RECORD
