Metadata-Version: 2.4
Name: earthscale
Version: 0.15.0
Summary: Client for the Earthscale HTTP API
Requires-Python: >=3.10
Requires-Dist: click
Requires-Dist: pydantic-settings>=2
Requires-Dist: pydantic>=2
Requires-Dist: requests
Requires-Dist: supabase
